<?xml version="1.0" encoding="UTF-8"?>
<factura id="comprobante" version="1.0.0">
    <infoTributaria>
        <ambiente>1</ambiente>
        <tipoEmision>1</tipoEmision>
        <razonSocial>Dreconstec</razonSocial>
        <nombreComercial>Dreconstec</nombreComercial>
        <ruc>0919664854001</ruc>
        <claveAcceso>0208202201091966485400110010010000010800000000117</claveAcceso>
        <codDoc>01</codDoc>
        <estab>001</estab>
        <ptoEmi>001</ptoEmi>
        <secuencial>000001080</secuencial>
        <dirMatriz>PASAJE A LOTE 2 S/N Y 4 DE MARZO</dirMatriz>
    </infoTributaria>
    <infoFactura>
        <fechaEmision>02/08/2022</fechaEmision>
        <dirEstablecimiento>PASAJE A LOTE 2 S/N Y 4 DE MARZO</dirEstablecimiento>
        <obligadoContabilidad>SI</obligadoContabilidad>       
        <tipoIdentificacionComprador>04</tipoIdentificacionComprador>
        
        <razonSocialComprador>Alexandra Albornoz Ortiz</razonSocialComprador>
        <identificacionComprador>0919664854001</identificacionComprador>
        <direccionComprador>Conjunto Brasil 2 Casa 32</direccionComprador><totalSinImpuestos>1159.74</totalSinImpuestos><totalDescuento>0</totalDescuento><totalConImpuestos>
        <totalImpuesto>
                        <codigo>2</codigo>
                        <codigoPorcentaje>0</codigoPorcentaje>
                        <baseImponible>1159.74</baseImponible>
                        <tarifa>0</tarifa>                
                        <valor>0.00</valor>
                    </totalImpuesto>
         </totalConImpuestos>        
        <propina>0.00</propina>        
        <importeTotal>1159.74</importeTotal>
        <moneda>DOLAR</moneda>
        <pagos>
            <pago>
                <formaPago>20</formaPago>
                <total>1159.74</total>
                <plazo>1</plazo>
                <unidadTiempo>Dias</unidadTiempo>
            </pago>            
        </pagos>
        <valorRetIva>0.00</valorRetIva>
        <valorRetRenta>0.00</valorRetRenta>
    </infoFactura>
    <detalles><detalle>
            <codigoPrincipal>25</codigoPrincipal>
            <codigoAuxiliar>25</codigoAuxiliar>
            <descripcion>Pulpa de COCO</descripcion>
            <cantidad>2</cantidad>
            <precioUnitario>3.37</precioUnitario>            
            <descuento>0</descuento>
            <precioTotalSinImpuesto>6.74</precioTotalSinImpuesto>
            <detallesAdicionales>
                <detAdicional nombre="denominacion_tipo_producto" valor="Tipo Producto"></detAdicional>
                <detAdicional nombre="denominacion_categoria" valor="Categoria"></detAdicional>
            </detallesAdicionales><impuestos>
                <impuesto>
                    <codigo>2</codigo>
                    <codigoPorcentaje>0</codigoPorcentaje>
                    <tarifa>0</tarifa>
                    <baseImponible>6.74</baseImponible>
                    <valor>0</valor>
                </impuesto>
            </impuestos></detalle><detalle>
            <codigoPrincipal>26</codigoPrincipal>
            <codigoAuxiliar>26</codigoAuxiliar>
            <descripcion>Pulpa de NARANJILLA CMP</descripcion>
            <cantidad>900</cantidad>
            <precioUnitario>0.25</precioUnitario>            
            <descuento>0</descuento>
            <precioTotalSinImpuesto>225.00</precioTotalSinImpuesto>
            <detallesAdicionales>
                <detAdicional nombre="denominacion_tipo_producto" valor="Tipo Producto"></detAdicional>
                <detAdicional nombre="denominacion_categoria" valor="Categoria"></detAdicional>
            </detallesAdicionales><impuestos>
                <impuesto>
                    <codigo>2</codigo>
                    <codigoPorcentaje>0</codigoPorcentaje>
                    <tarifa>0</tarifa>
                    <baseImponible>225.00</baseImponible>
                    <valor>0</valor>
                </impuesto>
            </impuestos></detalle><detalle>
            <codigoPrincipal>27</codigoPrincipal>
            <codigoAuxiliar>27</codigoAuxiliar>
            <descripcion>Pulpa de GUANABANA CMP</descripcion>
            <cantidad>1600</cantidad>
            <precioUnitario>0.31</precioUnitario>            
            <descuento>0</descuento>
            <precioTotalSinImpuesto>496.00</precioTotalSinImpuesto>
            <detallesAdicionales>
                <detAdicional nombre="denominacion_tipo_producto" valor="Tipo Producto"></detAdicional>
                <detAdicional nombre="denominacion_categoria" valor="Categoria"></detAdicional>
            </detallesAdicionales><impuestos>
                <impuesto>
                    <codigo>2</codigo>
                    <codigoPorcentaje>0</codigoPorcentaje>
                    <tarifa>0</tarifa>
                    <baseImponible>496.00</baseImponible>
                    <valor>0</valor>
                </impuesto>
            </impuestos></detalle><detalle>
            <codigoPrincipal>28</codigoPrincipal>
            <codigoAuxiliar>28</codigoAuxiliar>
            <descripcion>Pulpa de MORA CAMP</descripcion>
            <cantidad>1600</cantidad>
            <precioUnitario>0.27</precioUnitario>            
            <descuento>0</descuento>
            <precioTotalSinImpuesto>432.00</precioTotalSinImpuesto>
            <detallesAdicionales>
                <detAdicional nombre="denominacion_tipo_producto" valor="Tipo Producto"></detAdicional>
                <detAdicional nombre="denominacion_categoria" valor="Categoria"></detAdicional>
            </detallesAdicionales><impuestos>
                <impuesto>
                    <codigo>2</codigo>
                    <codigoPorcentaje>0</codigoPorcentaje>
                    <tarifa>0</tarifa>
                    <baseImponible>432.00</baseImponible>
                    <valor>0</valor>
                </impuesto>
            </impuestos></detalle></detalles>
    <infoAdicional>
        <campoAdicional nombre="Direccion">Conjunto Brasil 2 Casa 32</campoAdicional>
        <campoAdicional nombre="Telefono">2419867</campoAdicional>        
        <campoAdicional nombre="Email">kaceto104@gmail.com</campoAdicional>
    </infoAdicional>
</factura>